dyad_github/__init__.py
dyad_github/agent.py
dyad_github/dyad-extension.toml
dyad_github/pr_fetcher.py
dyad_github/pr_parser.py
dyad_github/prompt.py
dyad_github/py.typed
dyad_github-0.1.7.dist-info/METADATA
dyad_github-0.1.7.dist-info/WHEEL
dyad_github-0.1.7.dist-info/RECORD
