Metadata-Version: 2.4
Name: dyad-github
Version: 0.1.7
Summary: Add your description here
Requires-Python: >=3.10
Requires-Dist: requests>=2.32.3
